hashub_vector/__init__.py
hashub_vector/client.py
hashub_vector/exceptions.py
hashub_vector/models.py
hashub_vector/py.typed
hashub_vector-1.0.0.dist-info/licenses/LICENSE
hashub_vector-1.0.0.dist-info/METADATA
hashub_vector-1.0.0.dist-info/WHEEL
hashub_vector-1.0.0.dist-info/top_level.txt
hashub_vector-1.0.0.dist-info/RECORD
