Metadata-Version: 2.4
Name: hashub-vector
Version: 1.0.0
Summary: Python SDK for Hashub Vector API - High-quality multilingual text embeddings
Author-email: Hashub Team <support@hashub.dev>
License: MIT
Project-URL: Homepage, https://github.com/hasanbahadir/hashub-vector-sdk
Project-URL: Documentation, https://github.com/hasanbahadir/hashub-vector-sdk#readme
Project-URL: Repository, https://github.com/hasanbahadir/hashub-vector-sdk
Project-URL: Issues, https://github.com/hasanbahadir/hashub-vector-sdk/issues
Project-URL: Changelog, https://github.com/hasanbahadir/hashub-vector-sdk/blob/master/CHANGELOG.md
Keywords: embeddings,vector,nlp,ai,machine-learning,text-processing,multilingual,turkish,semantic-search,rag,retrieval
Classifier: Development Status :: 5 - Production/Stable
Classifier: Intended Audience :: Developers
Classifier: License :: OSI Approved :: MIT License
Classifier: Operating System :: OS Independent
Classifier: Programming Language :: Python :: 3
Classifier: Programming Language :: Python :: 3.8
Classifier: Programming Language :: Python :: 3.9
Classifier: Programming Language :: Python :: 3.10
Classifier: Programming Language :: Python :: 3.11
Classifier: Programming Language :: Python :: 3.12
Classifier: Topic :: Scientific/Engineering :: Artificial Intelligence
Classifier: Topic :: Software Development :: Libraries :: Python Modules
Classifier: Topic :: Text Processing :: Linguistic
Requires-Python: >=3.8
License-File: LICENSE
Requires-Dist: httpx>=0.24.0
Requires-Dist: typing-extensions>=4.0.0; python_version < "3.10"
Provides-Extra: dev
Requires-Dist: pytest>=7.0.0; extra == "dev"
Requires-Dist: pytest-asyncio>=0.21.0; extra == "dev"
Requires-Dist: pytest-cov>=4.0.0; extra == "dev"
Requires-Dist: black>=23.0.0; extra == "dev"
Requires-Dist: isort>=5.12.0; extra == "dev"
Requires-Dist: flake8>=6.0.0; extra == "dev"
Requires-Dist: mypy>=1.0.0; extra == "dev"
Requires-Dist: pre-commit>=3.0.0; extra == "dev"
Provides-Extra: docs
Requires-Dist: mkdocs>=1.5.0; extra == "docs"
Requires-Dist: mkdocs-material>=9.0.0; extra == "docs"
Requires-Dist: mkdocstrings[python]>=0.22.0; extra == "docs"
Provides-Extra: examples
Requires-Dist: numpy>=1.21.0; extra == "examples"
Requires-Dist: pandas>=1.3.0; extra == "examples"
Requires-Dist: scikit-learn>=1.0.0; extra == "examples"
Requires-Dist: langchain>=0.1.0; extra == "examples"
Requires-Dist: llama-index>=0.9.0; extra == "examples"
Dynamic: license-file
